BubotObj/OcfDevice/subtype/DimmerWBMRGBWD/DimmerWBMRGBWD.json
BubotObj/OcfDevice/subtype/DimmerWBMRGBWD/DimmerWBMRGBWD.py
BubotObj/OcfDevice/subtype/DimmerWBMRGBWD/__init__.py
BubotObj/OcfDevice/subtype/DimmerWBMRGBWD/lib/ColorHelper.py
BubotObj/OcfDevice/subtype/DimmerWBMRGBWD/lib/TestWirenBoardDimmer.py
BubotObj/OcfDevice/subtype/DimmerWBMRGBWD/lib/WirenBoardDimmer.json
BubotObj/OcfDevice/subtype/DimmerWBMRGBWD/lib/WirenBoardDimmer.py
BubotObj/OcfDevice/subtype/DimmerWBMRGBWD/lib/__init__.py
BubotObj/OcfDevice/subtype/RelayWBMR6C/RelayWBMR6C.json
BubotObj/OcfDevice/subtype/RelayWBMR6C/RelayWBMR6C.py
BubotObj/OcfDevice/subtype/RelayWBMR6C/__init__.py
BubotObj/OcfDevice/subtype/RelayWBMR6C/lib/TestWirenBoardRelay.py
BubotObj/OcfDevice/subtype/RelayWBMR6C/lib/WirenBoardRelay.json
BubotObj/OcfDevice/subtype/RelayWBMR6C/lib/WirenBoardRelay.py
BubotObj/OcfDevice/subtype/RelayWBMR6C/lib/__init__.py
Bubot_WirenBoard-0.0.2.dist-info/LICENSE
Bubot_WirenBoard-0.0.2.dist-info/METADATA
Bubot_WirenBoard-0.0.2.dist-info/WHEEL
Bubot_WirenBoard-0.0.2.dist-info/top_level.txt
Bubot_WirenBoard-0.0.2.dist-info/RECORD
